django_accounts_management/__init__.py
django_accounts_management/admin.py
django_accounts_management/apps.py
django_accounts_management/decorators.py
django_accounts_management/exceptions.py
django_accounts_management/forms.py
django_accounts_management/models.py
django_accounts_management/signals.py
django_accounts_management/tests.py
django_accounts_management/views.py
django_accounts_management/migrations/0001_initial.py
django_accounts_management/migrations/__init__.py
py_accounts_management-0.1.5.dist-info/licenses/LICENSE
py_accounts_management-0.1.5.dist-info/METADATA
py_accounts_management-0.1.5.dist-info/WHEEL
py_accounts_management-0.1.5.dist-info/top_level.txt
py_accounts_management-0.1.5.dist-info/RECORD
